[
  {"english":"Key","gujarati":"ચાવી"},
  {"english":"Kid","gujarati":"બાળક"},
  {"english":"Kidney","gujarati":"કિડની"},
  {"english":"Kill","gujarati":"મારવું"},
  {"english":"Kind","gujarati":"દયાળુ"},
  {"english":"Kindness","gujarati":"દયાળુતા"},
  {"english":"King","gujarati":"રાજા"},
  {"english":"Kingdom","gujarati":"રાજ્ય"},
  {"english":"Kiss","gujarati":"ચુંબન"},
  {"english":"Kitchen","gujarati":"રસોડું"},
  {"english":"Kite","gujarati":"પતંગ"},
  {"english":"Kitten","gujarati":"બિલાડીનું બચ્ચું"},
  {"english":"Knife","gujarati":"છરી"},
  {"english":"Knock","gujarati":"ટકોરો મારવો"},
  {"english":"Knee","gujarati":"ઘૂંટણ"},
  {"english":"Know","gujarati":"જાણવું"},
  {"english":"Knowledge","gujarati":"જ્ઞાન"},
  {"english":"Keyboard","gujarati":"કીબોર્ડ"},
  {"english":"Keychain","gujarati":"ચાવીની ચેન"},
  {"english":"Kilogram","gujarati":"કિલોગ્રામ"},
  {"english":"Kilometer","gujarati":"કિલોમીટર"},
  {"english":"Kitchenware","gujarati":"રસોડાના વાસણો"},
  {"english":"Ketchup","gujarati":"કેચઅપ"},
  {"english":"Kernel","gujarati":"દાણો"},
  {"english":"Kick","gujarati":"લાત મારવી"},
  {"english":"Kidnap","gujarati":"અપહરણ કરવું"},
  {"english":"Killer","gujarati":"ખૂની"},
  {"english":"Kindergarten","gujarati":"બાળમંદિર"},
  {"english":"Kingfisher","gujarati":"કલકલિયો પક્ષી"},
  {"english":"Kiosk","gujarati":"નાનો સ્ટોલ"},
  {"english":"Kitchen Knife","gujarati":"રસોડાની છરી"},
  {"english":"Knitting","gujarati":"ગૂંથકામ"},
  {"english":"Knob","gujarati":"હેન્ડલ"},
  {"english":"Knight","gujarati":"શૂરવીર"},
  {"english":"Kettle","gujarati":"કેટલી"},
  {"english":"Keeper","gujarati":"રક્ષક"},
  {"english":"Keenness","gujarati":"ઉત્સુકતા"},
  {"english":"Keyword","gujarati":"મુખ્ય શબ્દ"},
  {"english":"Kickoff","gujarati":"શરૂઆત"},
  {"english":"Kiddo","gujarati":"બાળક"},
  {"english":"Kitchen Table","gujarati":"રસોડાની ટેબલ"},
  {"english":"Knowledgeable","gujarati":"જ્ઞાની"},
  {"english":"Karma","gujarati":"કર્મ"},
  {"english":"Krypton","gujarati":"ક્રિપ્ટોન"},
  {"english":"Kangaroo","gujarati":"કાંગારૂ"},
  {"english":"Karate","gujarati":"કરાટે"},
  {"english":"Kayak","gujarati":"હોડી"},
  {"english":"Keeper Room","gujarati":"રક્ષકનું રૂમ"},
  {"english":"King Size","gujarati":"મોટા કદનું"},
  {"english":"Knowledge Base","gujarati":"જ્ઞાન ભંડાર"}
]